{
  "resourceType": "Bundle",
  "id": "multi-resource-patch-bundle",
  "type": "transaction",
  "entry": [
    {
      "resource": {
        "resourceType": "Parameters",
        "parameter": [
          {
            "name": "operation",
            "part": [
              {
                "name": "type",
                "valueCode": "replace"
              },
              {
                "name": "path",
                "valueString": "AllergyIntolerance.clinicalStatus"
              },
              {
                "name": "value",
                "valueCodeableConcept": {
                  "coding": [
                    {
                      "system": "http://terminology.hl7.org/CodeSystem/allergyintolerance-clinical",
                      "code": "resolved",
                      "display": "Resolved"
                    }
                  ]
                }
              }
            ]
          }
        ]
      },
      "request": {
        "method": "PATCH",
        "url": "AllergyIntolerance/allergy-123"
      }
    },
    {
      "resource": {
        "resourceType": "Parameters",
        "parameter": [
          {
            "name": "operation",
            "part": [
              {
                "name": "type",
                "valueCode": "replace"
              },
              {
                "name": "path",
                "valueString": "AllergyIntolerance.clinicalStatus"
              },
              {
                "name": "value",
                "valueCodeableConcept": {
                  "coding": [
                    {
                      "system": "http://terminology.hl7.org/CodeSystem/allergyintolerance-clinical",
                      "code": "active",
                      "display": "Active"
                    }
                  ]
                }
              }
            ]
          }
        ]
      },
      "request": {
        "method": "PATCH",
        "url": "AllergyIntolerance/allergy-123"
      }
    },
    {
      "resource": {
        "resourceType": "Parameters",
        "parameter": [
          {
            "name": "operation",
            "part": [
              {
                "name": "type",
                "valueCode": "replace"
              },
              {
                "name": "path",
                "valueString": "Condition.clinicalStatus"
              },
              {
                "name": "value",
                "valueCodeableConcept": {
                  "coding": [
                    {
                      "system": "http://terminology.hl7.org/CodeSystem/condition-clinical",
                      "code": "inactive",
                      "display": "Inactive"
                    }
                  ]
                }
              }
            ]
          }
        ]
      },
      "request": {
        "method": "PATCH",
        "url": "Condition/condition-456"
      }
    },
    {
      "resource": {
        "resourceType": "Parameters",
        "parameter": [
          {
            "name": "operation",
            "part": [
              {
                "name": "type",
                "valueCode": "replace"
              },
              {
                "name": "path",
                "valueString": "Condition.clinicalStatus"
              },
              {
                "name": "value",
                "valueCodeableConcept": {
                  "coding": [
                    {
                      "system": "http://terminology.hl7.org/CodeSystem/condition-clinical",
                      "code": "active",
                      "display": "Active"
                    }
                  ]
                }
              }
            ]
          }
        ]
      },
      "request": {
        "method": "PATCH",
        "url": "Condition/condition-456"
      }
    },
    {
      "resource": {
        "resourceType": "Parameters",
        "parameter": [
          {
            "name": "operation",
            "part": [
              {
                "name": "type",
                "valueCode": "replace"
              },
              {
                "name": "path",
                "valueString": "MedicationStatement.status"
              },
              {
                "name": "value",
                "valueCode": "stopped"
              }
            ]
          }
        ]
      },
      "request": {
        "method": "PATCH",
        "url": "MedicationStatement/medstmt-789"
      }
    },
    {
      "resource": {
        "resourceType": "Parameters",
        "parameter": [
          {
            "name": "operation",
            "part": [
              {
                "name": "type",
                "valueCode": "replace"
              },
              {
                "name": "path",
                "valueString": "MedicationStatement.status"
              },
              {
                "name": "value",
                "valueCode": "active"
              }
            ]
          }
        ]
      },
      "request": {
        "method": "PATCH",
        "url": "MedicationStatement/medstmt-789"
      }
    },
    {
      "resource": {
        "resourceType": "Parameters",
        "parameter": [
          {
            "name": "operation",
            "part": [
              {
                "name": "type",
                "valueCode": "replace"
              },
              {
                "name": "path",
                "valueString": "Patient.gender"
              },
              {
                "name": "value",
                "valueCode": "other"
              }
            ]
          }
        ]
      },
      "request": {
        "method": "PATCH",
        "url": "Patient/patient-101"
      }
    },
    {
      "resource": {
        "resourceType": "Parameters",
        "parameter": [
          {
            "name": "operation",
            "part": [
              {
                "name": "type",
                "valueCode": "replace"
              },
              {
                "name": "path",
                "valueString": "Patient.gender"
              },
              {
                "name": "value",
                "valueCode": "female"
              }
            ]
          }
        ]
      },
      "request": {
        "method": "PATCH",
        "url": "Patient/patient-101"
      }
    }
  ]
}